Workbook

Sheet Cover
A1: TD POWER SYSTEMS LTD (NSE: TDPOWERSYS)
A2: Equity Research Report | Initiating Coverage | BUY
A3: Sector: Heavy Electrical Equipment | Industry: Capital Goods | February 2026
A5: Metric | B5: Value | D5: Metric | E5: Value
A6: CMP (INR) | B6: 883 | D6: 52W High / Low | E6: 850 / 293
A7: Target Price (INR) | B7: 933 | D7: Market Cap (INR Cr) | E7: 13787
A8: Upside / Downside | B8: 0.057 | D8: EV (INR Cr) | E8: 13574
A9: Rating | B9: ACCUMULATE | D9: Shares Outstanding (Cr) | E9: 15.6
A10: FY25 Revenue (INR Cr) | B10: 1279 | D10: Free Float (%) | E10: 73.1%
A11: FY25 EBITDA (INR Cr) | B11: 235 | D11: ROCE (%) | E11: 0.25
A12: FY25 PAT (INR Cr) | B12: 175 | D12: ROE (%) | E12: 22.3%
A13: FY25 EPS (INR) | B13: 11.18 | D13: P/E (TTM) | E13: 66.2
A14: FY25 EBITDA Margin | B14: 18.4% | D14: EV/EBITDA (TTM) | E14: 49.1
A15: Revenue CAGR (FY22-25) | B15: 17.1% | D15: Dividend Yield (%) | E15: 0.18%
A16: PAT CAGR (FY22-25) | B16: 36.0% | D16: Book Value/Share | E16: 61.6
A17: Order Book (INR Cr) | B17: 1845 | D17: Export % of Orders (Q3FY26) | E17: 84%
A19: INVESTMENT THESIS
A20: 1. Export-led growth: 84% of Q3FY26 orders from exports; management guides export > domestic in FY27/28
A21: 2. New plant ramp-up: Tumkuru Plant 3 commissioned; revenue ramp from Q4FY26 to significantly expand capacity
A22: 3. Diversification: Traction motors (5-yr EUR contract ₹300 Cr), nuclear orders, data center generators
A23: 4. Margin expansion: EBITDA margins improved from 12% (FY22) to 18%+ (FY25); mix shift to exports & large units
A24: 5. Global installed base: 6,500+ units across 105 countries; aftermarket / spares growing as recurring revenue
A25: 6. Strong order book: ₹1,845 Cr order book (Dec'25) = ~1.4x FY25 revenue; strong visibility into FY26/27
A26: Key Risk: Promoter holding reduced -31.7% over 3 yrs; customer concentration; commodity cost volatility

Sheet Historical Financials
A1: TD POWER SYSTEMS | HISTORICAL FINANCIAL SUMMARY (INR Crores)
A3: Income Statement | B3: FY19 | C3: FY20 | D3: FY21 | E3: FY22 | F3: FY23 | G3: FY24 | H3: FY25 | I3: FY26E* | J3: TTM
A5: Revenue | B5: 459 | C5: 515 | D5: 594 | E5: 797 | F5: 872 | G5: 1001 | H5: 1279 | I5: 1599 | J5: 1599
A6: YoY Growth | B6: - | C6: =C5/B5-1 -> 0.12200436 | D6: =D5/C5-1 -> 0.15339806 | E6: =E5/D5-1 -> 0.34175084 | F6: =F5/E5-1 -> 0.094102886 | G6: =G5/F5-1 -> 0.14793578 | H6: =H5/G5-1 -> 0.27772228 | I6: =I5/H5-1 -> 0.25019547 | J6: =J5/I5-1 -> 0
A7: Material & Manufacturing Cost | B7: =B5*73% -> 335.07 | C7: =C5*73% -> 375.95 | D7: =D5*69% -> 409.86 | E7: =E5*73% -> 581.81 | F7: =F5*70% -> 610.4 | G7: =G5*68% -> 680.68 | H7: =H5*67% -> 856.93 | I7: =I5*67% -> 1071.33 | J7: =J5*67% -> 1071.33
A8: Gross Profit | B8: =B5-B7 -> 123.93 | C8: =C5-C7 -> 139.05 | D8: =D5-D7 -> 184.14 | E8: =E5-E7 -> 215.19 | F8: =F5-F7 -> 261.6 | G8: =G5-G7 -> 320.32 | H8: =H5-H7 -> 422.07 | I8: =I5-I7 -> 527.67 | J8: =J5-J7 -> 527.67
A9: Gross Margin | B9: =B8/B5 -> 0.27 | C9: =C8/C5 -> 0.27 | D9: =D8/D5 -> 0.31 | E9: =E8/E5 -> 0.27 | F9: =F8/F5 -> 0.3 | G9: =G8/G5 -> 0.32 | H9: =H8/H5 -> 0.33 | I9: =I8/I5 -> 0.33 | J9: =J8/J5 -> 0.33
A10: EBITDA | B10: 30 | C10: 38 | D10: 71 | E10: 97 | F10: 134 | G10: 171 | H10: 235 | I10: 296 | J10: 282
A11: EBITDA Margin | B11: =B10/B5 -> 0.065359477 | C11: =C10/C5 -> 0.073786408 | D11: =D10/D5 -> 0.11952862 | E11: =E10/E5 -> 0.1217064 | F11: =F10/F5 -> 0.15366972 | G11: =G10/G5 -> 0.17082917 | H11: =H10/H5 -> 0.18373729 | I11: =I10/I5 -> 0.1851157 | J11: =J10/J5 -> 0.17636023
A12: Depreciation | B12: 26 | C12: 22 | D12: 22 | E12: 22 | F12: 21 | G12: 21 | H12: 20 | I12: 21 | J12: 21
A13: EBIT | B13: =B10-B12 -> 4 | C13: =C10-C12 -> 16 | D13: =D10-D12 -> 49 | E13: =E10-E12 -> 75 | F13: =F10-F12 -> 113 | G13: =G10-G12 -> 150 | H13: =H10-H12 -> 215 | I13: =I10-I12 -> 275 | J13: =J10-J12 -> 261
A14: Interest | B14: 6 | C14: 10 | D14: 9 | E14: 7 | F14: 4 | G14: 4 | H14: 8 | I14: 2 | J14: 2
A15: PBT | B15: =B13-B14 -> -2 | C15: =C13-C14 -> 6 | D15: =D13-D14 -> 40 | E15: =E13-E14 -> 68 | F15: =F13-F14 -> 109 | G15: =G13-G14 -> 146 | H15: =H13-H14 -> 207 | I15: =I13-I14 -> 273 | J15: =J13-J14 -> 259
A16: Tax | B16: 4 | C16: 3 | D16: 11 | E16: 21 | F16: 33 | G16: 44 | H16: 57 | I16: 69 | J16: 69
A17: Net Profit | B17: 3 | C17: 30 | D17: 45 | E17: 70 | F17: 97 | G17: 118 | H17: 175 | I17: 208 | J17: 208
A18: Net Margin | B18: =B17/B5 -> 0.0065359477 | C18: =C17/C5 -> 0.058252427 | D18: =D17/D5 -> 0.075757576 | E18: =E17/E5 -> 0.08782936 | F18: =F17/F5 -> 0.11123853 | G18: =G17/G5 -> 0.11788212 | H18: =H17/H5 -> 0.13682565 | I18: =I17/I5 -> 0.1300813 | J18: =J17/J5 -> 0.1300813
A19: EPS (INR) | B19: 0.2 | C19: 1.94 | D19: 2.92 | E19: 4.53 | F19: 6.2 | G19: 7.58 | H19: 11.18 | I19: 13.33 | J19: 13.33
A20: ROCE | H20: =H13/H26 -> 0.25
A22: BALANCE SHEET SUMMARY
A23: Balance Sheet | B23: FY19 | C23: FY20 | D23: FY21 | E23: FY22 | F23: FY23 | G23: FY24 | H23: FY25 | I23: FY26E* | J23: TTM
A24: Equity Capital | B24: 31 | C24: 31 | D24: 31 | E24: 31 | F24: 31 | G24: 31 | H24: 31 | I24: 31 | J24: -
A25: Reserves | B25: 385 | C25: 394 | D25: 440 | E25: 496 | F25: 573 | G25: 674 | H25: 829 | I25: - | J25: -
A26: Total Equity | B26: =B24+B25 -> 416 | C26: =C24+C25 -> 425 | D26: =D24+D25 -> 471 | E26: =E24+E25 -> 527 | F26: =F24+F25 -> 604 | G26: =G24+G25 -> 705 | H26: =H24+H25 -> 860 | I26: - | J26: -
A27: Borrowings | B27: 61 | C27: 68 | D27: 52 | E27: 71 | F27: 0 | G27: 0 | H27: 12 | I27: 12 | J27: -
A28: Trade Payables | B28: 168 | C28: 144 | D28: 108 | E28: 151 | F28: 131 | G28: 140 | H28: 231 | I28: 231 | J28: -
A29: Total Assets | B29: 696 | C29: 754 | D29: 785 | E29: 862 | F29: 930 | G29: 1098 | H29: 1320 | I29: - | J29: -
A30: Cash & Equivalents | B30: 84 | C30: 110 | D30: 150 | E30: 190 | F30: 260 | G30: 300 | H30: 280 | I30: - | J30: -
A31: Net Debt | B31: =B27-B30 -> -23 | C31: =C27-C30 -> -42 | D31: =D27-D30 -> -98 | E31: =E27-E30 -> -119 | F31: =F27-F30 -> -260 | G31: =G27-G30 -> -300 | H31: =H27-H30 -> -268 | I31: - | J31: -
A32: Working Capital | B32: =539-271 -> 268 | C32: =557-265 -> 292 | D32: =590-262 -> 328 | E32: =720-309 -> 411 | F32: =720-299 -> 421 | G32: =842-333 -> 509 | H32: =1140-491 -> 649 | I32: - | J32: -
A33: ROCE (%) | B33: - | C33: - | D33: - | E33: - | F33: - | G33: - | H33: =H13/H26 -> 0.25 | I33: - | J33: -
A35: CASH FLOW SUMMARY
A36: Cash Flow | B36: FY19 | C36: FY20 | D36: FY21 | E36: FY22 | F36: FY23 | G36: FY24 | H36: FY25 | I36: FY26E* | J36: TTM
A37: CFO | B37: 48 | C37: 56 | D37: -3 | E37: 11 | F37: 89 | G37: 84 | H37: 40 | I37: - | J37: -
A38: Capex | B38: -13 | C38: -13 | D38: -15 | E38: -15 | F38: -21 | G38: -45 | H38: -56 | I38: - | J38: -
A39: FCFF | B39: =B37+B38 -> 35 | C39: =C37+C38 -> 43 | D39: =D37+D38 -> -18 | E39: =E37+E38 -> -4 | F39: =F37+F38 -> 68 | G39: =G37+G38 -> 39 | H39: =H37+H38 -> -16 | I39: - | J39: -
A40: CFI | B40: -13 | C40: 0 | D40: -11 | E40: -14 | F40: -13 | G40: -34 | H40: -34 | I40: - | J40: -
A41: CFF | B41: -45 | C41: -17 | D41: -20 | E41: 11 | F41: -89 | G41: -16 | H41: -7 | I41: - | J41: -
A42: Net Cash Change | B42: =B37+B40+B41 -> -10 | C42: =C37+C40+C41 -> 39 | D42: =D37+D40+D41 -> -34 | E42: =E37+E40+E41 -> 8 | F42: =F37+F40+F41 -> -13 | G42: =G37+G40+G41 -> 34 | H42: =H37+H40+H41 -> -1 | I42: - | J42: -

Sheet DCF Valuation
A1: TD POWER SYSTEMS | DISCOUNTED CASH FLOW VALUATION
A3: METHODOLOGY: TDPS is a high-growth company. Two approaches used: (1) DCF for fundamental intrinsic value floor; (2) Forward P/E & EV/EBITDA on FY27E estimates for 12-month target price. Both outputs are shown and cross-referenced.
A5: PART 1 — KEY DCF ASSUMPTIONS (Blue = Input, Yellow = Change to run scenarios)
A6: Assumption | B6: Value | D6: Note / Source
A7: Base Year Revenue FY25A (INR Cr) | B7: 1279 | C7: ◄ Input | D7: Actuals — Company Q3FY26 Results presentation
A8: Revenue Growth — FY26E | B8: 0.25 | C8: ◄ Input | D8: Conservative end of mgmt guide; backed by ₹1,845 Cr order book (1.4x FY25 rev)
A9: Revenue Growth — FY27E | B9: 0.22 | C9: ◄ Input | D9: Export ramp + Plant 3 (Tumkuru) operating at full run-rate
A10: Revenue Growth — FY28E | B10: 0.18 | C10: ◄ Input | D10: Normalization phase; slower export growth
A11: Revenue Growth — FY29E | B11: 0.15 | C11: ◄ Input | D11: Approaching steady-state
A12: Revenue Growth — FY30E | B12: 0.12 | C12: ◄ Input | D12: Mature growth phase
A13: EBITDA Margin — FY26E | B13: 0.185 | C13: ◄ Input | D13: Marginal expansion; operating leverage vs. higher export logistics costs
A14: EBITDA Margin — FY27E | B14: 0.19 | C14: ◄ Input | D14: Scale benefits from Plant 3 + better product mix
A15: EBITDA Margin — FY28-30E | B15: 0.2 | C15: ◄ Input | D15: Target steady-state; premium products + export dominance
A16: D&A as % of Revenue | B16: 0.016 | C16: ◄ Input | D16: Asset-light ETO model; consistent with FY25 run-rate
A17: Capex % Revenue (FY26-27E) | B17: 0.03 | C17: ◄ Input | D17: 3% normalized capex; Plant 3 commissioned FY26 — elevated phase now complete
A18: Change in WC as % of Revenue | B18: 0.05 | C18: ◄ Input | D18: conservative estimate due to expansion
... A24: Current Market Price — CMP (INR) | B24: 883 | C24: ◄ Input | D24: NSE closing price, Feb 26, 2026
A26: PART 2 — 5-YEAR FCFF PROJECTION (INR Crores) | Blue=Hardcoded Actuals Black=Formulas Green=Cross-sheet Links
A27: Line Item | B27: FY25A | C27: FY26E | D27: FY27E | E27: FY28E | F27: FY29E | G27: FY30E | H27: Terminal Value
A28: Revenue | B28: =B7 -> 1279 | C28: =B28*(1+B8) -> 1598.75 | D28: =C28*(1+B9) -> 1950.475 | E28: =D28*(1+B10) -> 2301.5605 | F28: =E28*(1+B11) -> 2646.7946 | G28: =F28*(1+B12) -> 2964.4099 | H28: -
A29: YoY Revenue Growth | B29: - | C29: =C28/B28-1 -> 0.25 | D29: =D28/C28-1 -> 0.22 | E29: =E28/D28-1 -> 0.18 | F29: =F28/E28-1 -> 0.15 | G29: =G28/F28-1 -> 0.12 | H29: -
A30: EBITDA | B30: 235 | C30: =C28*B13 -> 295.76875 | D30: =D28*B14 -> 370.59025 | E30: =E28*B15 -> 460.3121 | F30: =F28*B15 -> 529.35891 | G30: =G28*B15 -> 592.88198 | H30: -
A31: EBITDA Margin (%) | B31: =B30/B28 -> 0.18373729 | C31: =C30/C28 -> 0.185 | D31: =D30/D28 -> 0.19 | E31: =E30/E28 -> 0.2 | F31: =F30/F28 -> 0.2 | G31: =G30/G28 -> 0.2 | H31: -
A32: (-) Depreciation & Amortization | B32: =B28*B16 -> 20.464 | C32: =C28*B16 -> 25.58 | D32: =D28*B16 -> 31.2076 | E32: =E28*B16 -> 36.824968 | F32: =F28*B16 -> 42.348713 | G32: =G28*B16 -> 47.430559 | H32: -
A33: EBIT (Operating Profit after D&A) | B33: =B30-B32 -> 214.536 | C33: =C30-C32 -> 270.18875 | D33: =D30-D32 -> 339.38265 | E33: =E30-E32 -> 423.48713 | F33: =F30-F32 -> 487.0102 | G33: =G30-G32 -> 545.45143 | H33: -
A34: NOPAT = EBIT × (1 − Tax Rate) | B34: =B33*(1-B19) -> 160.902 | C34: =C33*(1-B19) -> 202.64156 | D34: =D33*(1-B19) -> 254.53699 | E34: =E33*(1-B19) -> 317.61535 | F34: =F33*(1-B19) -> 365.25765 | G34: =G33*(1-B19) -> 409.08857 | H34: -
A35: (+) Add Back: Depreciation & Amortization | B35: =B32 -> 20.464 | C35: =C32 -> 25.58 | D35: =D32 -> 31.2076 | E35: =E32 -> 36.824968 | F35: =F32 -> 42.348713 | G35: =G32 -> 47.430559 | H35: -
A36: (-) Capital Expenditure | B36: =B28*$B$17 -> 38.37 | C36: =C28*$B$17 -> 47.9625 | D36: =D28*$B$17 -> 58.51425 | E36: =E28*$B$17 -> 69.046815 | F36: =F28*$B$17 -> 79.403837 | G36: =G28*$B$17 -> 88.932298 | H36: -
A37: (-) Increase in Working Capital | B37: =B28*B18 -> 63.95 | C37: =C28*B18 -> 79.9375 | D37: =D28*B18 -> 97.52375 | E37: =E28*B18 -> 115.07802 | F37: =F28*B18 -> 132.33973 | G37: =G28*B18 -> 148.2205 | H37: -
A38: FREE CASH FLOW TO FIRM (FCFF) | B38: =B34+B35-B36-B37 -> 79.046 | C38: =C34+C35-C36-C37 -> 100.32156 | D38: =D34+D35-D36-D37 -> 129.70659 | E38: =E34+E35-E36-E37 -> 170.31548 | F38: =F34+F35-F36-F37 -> 195.8628 | G38: =G34+G35-G36-G37 -> 219.36633 | H38: =G38*(1+B21)/(B20-B21) -> 4187.9027
A39: Discount Factor [1/(1+WACC)^t] | B39: 1.000x | C39: =1/(1+B20)^1 -> 0.90497738 | D39: =1/(1+B20)^2 -> 0.81898405 | E39: =1/(1+B20)^3 -> 0.74116204 | F39: =1/(1+B20)^4 -> 0.67073487 | G39: =1/(1+B20)^5 -> 0.60699989 | H39: =1/(1+B20)^5 -> 0.60699989
A40: Present Value of FCFF | B40: - | C40: =C38*C39 -> 90.788744 | D40: =D38*D39 -> 106.22763 | E40: =E38*E39 -> 126.23137 | F40: =F38*F39 -> 131.37201 | G40: =G38*G39 -> 133.15534 | H40: =H38*H39 -> 2542.0565
A42: PART 3 — DCF VALUATION BRIDGE (INR Crores)
A43: Sum of PV(FCFF) — Explicit Period (FY26E–FY30E) | B43: =SUM(C40:G40) -> 587.77509
A44: PV of Terminal Value (Gordon Growth Model) | B44: =H40 -> 2542.0565
A45: Enterprise Value (EV = Sum PV_FCFF + PV_TV) | B45: =B43+B44 -> 3129.8316
A46: (+) Net Cash Position [Cash minus Borrowings] | B46: =B22 -> 268
A47: Equity Value [EV + Net Cash] | B47: =B45+B46 -> 3397.8316
A48: Shares Outstanding (Crores) | B48: =B23 -> 15.6
A49: DCF Intrinsic Value Per Share (INR) | B49: =B47/B48 -> 217.80972
A50: Current Market Price — CMP (INR) | B50: =B24 -> 883
A51: Market Premium over DCF Value | B51: =B50/B49-1 -> 3.0539973
A52: NOTE: TDPS trades at a premium to DCF intrinsic value because the market prices in 10+ years of growth. DCF value (₹170) = fundamental floor. Target price uses forward multiples (see Part 4).
A54: PART 4 — FORWARD MULTIPLES: 12-MONTH TARGET PRICE (Primary Valuation Method for High-Growth Companies)
A55: For TDPS — a high-growth, re-rating capital goods exporter — the market-anchored target price is derived from FY27E forward multiples, calibrated to the peer group premium.
A56: FY27E Estimates | B56: Value | C56: Derivation
A57: FY27E Revenue (INR Cr) | B57: =D28 -> 1950.475 | C57: Links to DCF projection row 28, column D
A58: FY27E EBITDA (INR Cr) | B58: =D30 -> 370.59025 | C58: Links to DCF projection row 30, column D
A59: FY27E PAT (INR Cr) | B59: 255 | C59: Est.: FY27E EBIT×0.75
A60: FY27E EPS (INR) | B60: =B59/B23 -> 16.346154
A62: Target Multiple | B62: Value | C62: Justification
A63: Target P/E (FY27E basis) | B63: 55 | C63: Peer median P/E 42x + 30% TDPS premium (superior growth: PAT CAGR 25%+, net cash, export expansion)
A64: Target EV/EBITDA (FY27E basis) | B64: 40 | C64: Peer median EV/EBITDA 28x + 43% TDPS premium (margin expansion trajectory, balance sheet quality) | D64: Peer median 23.9x + 67% TDPS premium (25%+ EPS CAGR, net cash, export moat, margin expansion)
A66: Methodology | B66: Implied Eq. Value (Cr) | C66: Implied Price (INR) | D66: Weight (%) | E66: Wtd. Contribution
A67: P/E Based Target Price | B67: =B60*B63*B23 -> 14025 | C67: =B60*B63 -> 899.03846 | D67: 0.5 | E67: =C67*D67 -> 449.51923
A68: EV/EBITDA Based Target Price | B68: =B58*B64+B22 -> 15091.61 | C68: =B68/B23 -> 967.4109 | D68: 0.5 | E68: =C68*D68 -> 483.70545
A70: BLENDED 12-MONTH TARGET PRICE (INR) | C70: =SUM(E67:E68)/SUM(D67:D68) -> 933.22468
A71: Current Market Price — CMP (INR) | C71: =B24 -> 883
A72: Upside / (Downside) to 12-Month Target | C72: =C70/C71-1 -> 0.056879592
A74: PART 5 — WACC DERIVATION
A75: Risk-Free Rate (Rf) | B75: 0.07 | C75: 10-year India G-Sec yield (Feb 2026)
A76: Equity Risk Premium (ERP) | B76: 0.08 | C76: India = Base ERP ~6% + Country Risk Premium ~2%
A77: Beta (β) | B77: 0.9 | C77: TDPS weekly raw beta vs. Nifty 500 (2-yr)
A78: Cost of Equity (Ke = Rf + β × ERP) | B78: =B75+B77*B76 -> 0.142 | C78: CAPM; links to inputs above
A79: Pre-Tax Cost of Debt (Kd) | B79: 0.085 | C79: Bank WC rate; company nearly debt-free
A80: After-Tax Cost of Debt = Kd×(1−Tax) | B80: =B79*(1-B19) -> 0.06375 | C80: Tax rate links to row 19
A81: Debt Weight (D/V) | B81: 0.05 | C81: Borrowings/(Equity+Debt)
A82: Equity Weight (E/V = 1 − D/V) | B82: =1-B81 -> 0.95
A83: WACC = Ke×E/V + Kd×(1-t)×D/V | B83: =B78*B82+B80*B81 -> 0.1380875 | C83: Should ≈ row 20 assumption
A84: Verification: WACC matches assumption? | B84: NOTE | C84: WACC=13.8% from CAPM; analyst override to 10.5% for quality premium (net-cash, FCF compounder, export moat). Sensitivity table covers 9%-14%.
A86: PART 6A — TARGET PRICE SENSITIVITY: P/E Multiple (rows) × FY27E EPS (cols) | Green = above CMP ₹883
A87: P/E \ EPS → | B87: ₹13.00 | C87: ₹15.00 | D87: 16 | E87: 16.35 | F87: ₹19.00 | G87: ₹21.00 | H87: ₹23.00
A88: 40 | B88: =$A$88*B87 -> 520 | C88: =$A$88*C87 -> 600 | D88: =$A$88*D87 -> 640 | E88: =$A$88*E87 -> 654 | F88: =$A$88*F87 -> 760 | G88: =$A$88*G87 -> 840 | H88: =$A$88*H87 -> 920
A89: 45 | B89: =$A$89*B87 -> 585 | C89: =$A$89*C87 -> 675 | D89: =$A$89*D87 -> 720 | E89: =$A$89*E87 -> 735.75 | F89: =$A$89*F87 -> 855 | G89: =$A$89*G87 -> 945 | H89: =$A$89*H87 -> 1035
A90: 50 | B90: =$A$90*B87 -> 650 | C90: =$A$90*C87 -> 750 | D90: =$A$90*D87 -> 800 | E90: =$A$90*E87 -> 817.5 | F90: =$A$90*F87 -> 950 | G90: =$A$90*G87 -> 1050 | H90: =$A$90*H87 -> 1150
A91: 55 | B91: =$A$91*B87 -> 715 | C91: =$A$91*C87 -> 825 | D91: =$A$91*D87 -> 880 | E91: =$A$91*E87 -> 899.25 | F91: =$A$91*F87 -> 1045 | G91: =$A$91*G87 -> 1155 | H91: =$A$91*H87 -> 1265
A92: 60 | B92: =$A$92*B87 -> 780 | C92: =$A$92*C87 -> 900 | D92: =$A$92*D87 -> 960 | E92: =$A$92*E87 -> 981 | F92: =$A$92*F87 -> 1140 | G92: =$A$92*G87 -> 1260 | H92: =$A$92*H87 -> 1380
A93: 65 | B93: =$A$93*B87 -> 845 | C93: =$A$93*C87 -> 975 | D93: =$A$93*D87 -> 1040 | E93: =$A$93*E87 -> 1062.75 | F93: =$A$93*F87 -> 1235 | G93: =$A$93*G87 -> 1365 | H93: =$A$93*H87 -> 1495
A94: 70 | B94: =$A$94*B87 -> 910 | C94: =$A$94*C87 -> 1050 | D94: =$A$94*D87 -> 1120 | E94: =$A$94*E87 -> 1144.5 | F94: =$A$94*F87 -> 1330 | G94: =$A$94*G87 -> 1470 | H94: =$A$94*H87 -> 1610
A96: PART 6B — TARGET PRICE SENSITIVITY: EV/EBITDA Multiple (rows) × FY27E EBITDA (cols, INR Cr) | Net Cash=₹268Cr, Shares=15.6 Cr
A97: EV/EBITDA \ EBITDA → | B97: 300 | C97: 340 | D97: 371 | E97: 400 | F97: 430 | G97: 460 | H97: 500
A98: 28 | B98: =($A$98*B97+268)/15.6 -> 555.64103 | C98: =($A$98*C97+268)/15.6 -> 627.4359 | D98: =($A$98*D97+268)/15.6 -> 683.07692 | E98: =($A$98*E97+268)/15.6 -> 735.12821 | F98: =($A$98*F97+268)/15.6 -> 788.97436 | G98: =($A$98*G97+268)/15.6 -> 842.82051 | H98: =($A$98*H97+268)/15.6 -> 914.61538
A99: 32 | B99: =($A$99*B97+268)/15.6 -> 632.5641 | C99: =($A$99*C97+268)/15.6 -> 714.61538 | D99: =($A$99*D97+268)/15.6 -> 778.20513 | E99: =($A$99*E97+268)/15.6 -> 837.69231 | F99: =($A$99*F97+268)/15.6 -> 899.23077 | G99: =($A$99*G97+268)/15.6 -> 960.76923 | H99: =($A$99*H97+268)/15.6 -> 1042.8205
A100: 36 | B100: =($A$100*B97+268)/15.6 -> 709.48718 | C100: =($A$100*C97+268)/15.6 -> 801.79487 | D100: =($A$100*D97+268)/15.6 -> 873.33333 | E100: =($A$100*E97+268)/15.6 -> 940.25641 | F100: =($A$100*F97+268)/15.6 -> 1009.4872 | G100: =($A$100*G97+268)/15.6 -> 1078.7179 | H100: =($A$100*H97+268)/15.6 -> 1171.0256
A101: 40 | B101: =($A$101*B97+268)/15.6 -> 786.41026 | C101: =($A$101*C97+268)/15.6 -> 888.97436 | D101: =($A$101*D97+268)/15.6 -> 968.46154 | E101: =($A$101*E97+268)/15.6 -> 1042.8205 | F101: =($A$101*F97+268)/15.6 -> 1119.7436 | G101: =($A$101*G97+268)/15.6 -> 1196.6667 | H101: =($A$101*H97+268)/15.6 -> 1299.2308
A102: 44 | B102: =($A$102*B97+268)/15.6 -> 863.33333 | C102: =($A$102*C97+268)/15.6 -> 976.15385 | D102: =($A$102*D97+268)/15.6 -> 1063.5897 | E102: =($A$102*E97+268)/15.6 -> 1145.3846 | F102: =($A$102*F97+268)/15.6 -> 1230 | G102: =($A$102*G97+268)/15.6 -> 1314.6154 | H102: =($A$102*H97+268)/15.6 -> 1427.4359
A103: 48 | B103: =($A$103*B97+268)/15.6 -> 940.25641 | C103: =($A$103*C97+268)/15.6 -> 1063.3333 | D103: =($A$103*D97+268)/15.6 -> 1158.7179 | E103: =($A$103*E97+268)/15.6 -> 1247.9487 | F103: =($A$103*F97+268)/15.6 -> 1340.2564 | G103: =($A$103*G97+268)/15.6 -> 1432.5641 | H103: =($A$103*H97+268)/15.6 -> 1555.641
A104: 52 | B104: =($A$104*B97+268)/15.6 -> 1017.1795 | C104: =($A$104*C97+268)/15.6 -> 1150.5128 | D104: =($A$104*D97+268)/15.6 -> 1253.8462 | E104: =($A$104*E97+268)/15.6 -> 1350.5128 | F104: =($A$104*F97+268)/15.6 -> 1450.5128 | G104: =($A$104*G97+268)/15.6 -> 1550.5128 | H104: =($A$104*H97+268)/15.6 -> 1683.8462

Sheet Comps Valuation
A1: TD POWER SYSTEMS | COMPARABLE COMPANY ANALYSIS (COMPS)
A3: Company | B3: Mkt Cap (Cr) | C3: FY26E Rev (Cr) | D3: FY26E EBITDA (Cr) | E3: FY26E PAT (Cr) | F3: FY26E P/E (x) | G3: FY26E EV/ EBITDA (x) | H3: P/B (x) | I3: EV/ Rev (x) | J3: EBITDA Mgn % | K3: ROE % | L3: ROCE %
A4: TD Power Systems | B4: 13787 | C4: 1599 | D4: 296 | E4: 218 | F4: 63.2 | G4: 45.8 | H4: 11.3 | I4: 8.5 | J4: 0.185 | K4: 0.223 | L4: 0.304
A5: Bharat Heavy Elec. | B5: 64000 | C5: 25000 | D5: 3500 | E5: 1600 | F5: 40 | G5: 18.3 | H5: 4 | I5: 2.5 | J5: 0.14 | K5: 0.1 | L5: 0.125
A6: CG Power & Ind Sol. | B6: 52000 | C6: 10500 | D6: 1750 | E6: 1150 | F6: 45.2 | G6: 29.7 | H6: 15 | I6: 5 | J6: 0.167 | K6: 0.34 | L6: 0.45
A7: Hitachi Energy India | B7: 15000 | C7: 5800 | D7: 800 | E7: 450 | F7: 33.3 | G7: 18.5 | H7: 8.8 | I7: 2.6 | J7: 0.138 | K7: 0.26 | L7: 0.315
A8: ABB India | B8: 65000 | C8: 13000 | D8: 2300 | E8: 1600 | F8: 40.6 | G8: 28.3 | H8: 10.2 | I8: 5 | J8: 0.177 | K8: 0.25 | L8: 0.308
A9: Siemens India | B9: 86000 | C9: 22000 | D9: 3600 | E9: 2400 | F9: 35.8 | G9: 23.9 | H9: 8.8 | I9: 3.9 | J9: 0.164 | K9: 0.24 | L9: 0.274
A10: Triveni Turbine | B10: 11000 | C10: 1750 | D10: 410 | E10: 245 | F10: 44.9 | G10: 26.8 | H10: 13.5 | I10: 6.3 | J10: 0.234 | K10: 0.285 | L10: 0.366
A11: Kirloskar Electric | B11: 1800 | C11: 920 | D11: 130 | E11: 72 | F11: 25 | G11: 13.8 | H11: 3.6 | I11: 2 | J11: 0.141 | K11: 0.135 | L11: 0.16
A12: Peer Median (ex-TDPS) | B12: =MEDIAN(B5:B11) -> 52000 | C12: =MEDIAN(C5:C11) -> 10500 | D12: =MEDIAN(D5:D11) -> 1750 | E12: =MEDIAN(E5:E11) -> 1150 | F12: =MEDIAN(F5:F11) -> 40 | G12: =MEDIAN(G5:G11) -> 23.9 | H12: =MEDIAN(H5:H11) -> 8.8 | I12: =MEDIAN(I5:I11) -> 3.9 | ... L12: =MEDIAN(L5:L11) -> 0.308
A13: Peer Average (ex-TDPS) | B13: =AVERAGE(B5:B11) -> 42114.286 | C13: =AVERAGE(C5:C11) -> 11281.429 | D13: =AVERAGE(D5:D11) -> 1784.2857 | E13: =AVERAGE(E5:E11) -> 1073.8571 | F13: =AVERAGE(F5:F11) -> 37.828571 | G13: =AVERAGE(G5:G11) -> 22.757143 | H13: =AVERAGE(H5:H11) -> 9.1285714 | I13: =AVERAGE(I5:I11) -> 3.9 | ... L13: =AVERAGE(L5:L11) -> 0.28542857
A15: PART 2 — IMPLIED VALUATION: TDPS at Peer Median Multiples vs Our Target Multiples (FY26E)
A16: Basis | B16: TDPS FY26E | C16: Peer Median Multiple | D16: Implied EV (Cr) | E16: Net Cash (Cr) | F16: Implied Eq. Value (Cr) | G16: Shares (Cr) | H16: Implied Price @Peer | I16: CMP | J16: (Disc.)/ Upside | K16: Target Multiple | L16: Target Price
A17: EV/EBITDA (FY26E) | B17: ='DCF Valuation'!C30 -> 295.76875 | C17: =G12 -> 23.9 | D17: =B17*C17 -> 7068.8731 | E17: 268 | F17: =D17+E17 -> 7336.8731 | G17: 15.6 | H17: =F17/G17 -> 470.31238 | I17: 883 | J17: =H17/I17-1 -> -0.4673699 | K17: 40 | L17: =(B17*K17+E17)/G17 -> 775.5609
A18: P/E (FY26E) | B18: 208 | C18: =F12 -> 40 | D18: N/A (equity) | E18: — | F18: =B18*C18 -> 8320 | G18: 15.6 | H18: =F18/G18 -> 533.33333 | I18: 883 | J18: =H18/I18-1 -> -0.39599849 | K18: 55 | L18: =B18/G18*K18 -> 733.33333
A19: EV/Revenue (FY26E) | B19: ='DCF Valuation'!C28 -> 1598.75 | C19: =I12 -> 3.9 | D19: =B19*C19 -> 6235.125 | E19: 268 | F19: =D19+E19 -> 6503.125 | G19: 15.6 | H19: =F19/G19 -> 416.86699 | I19: 883 | J19: =H19/I19-1 -> -0.52789696 | K19: 6 | L19: =(B19*K19+E19)/G19 -> 632.08333
A21: PART 3 — FOOTBALL FIELD: CONSOLIDATED VALUATION SUMMARY
A22: Methodology | B22: Low (INR) | C22: Base / Target (INR) | D22: High (INR) | E22: Weight | F22: Wtd. Contrib. | G22: Key Basis / Comment
A23: DCF (Fundamental Floor) | B23: 180 | C23: ='DCF Valuation'!B49 -> 217.80972 | D23: 250 | E23: 0 | F23: N/A | G23: 10-yr FCFF model @ WACC=10.5%, TGR=6%; fundamental floor — stock trades at ~4x intrinsic (growth premium)
A24: Forward P/E (FY27E) | B24: 720 | C24: ='DCF Valuation'!C67 -> 899.03846 | D24: 1200 | E24: 0.5 | F24: =C24*E24 -> 449.51923 | G24: 55x × FY27E EPS ₹17.44; links directly to DCF sheet Part 4 (cell C67)
A25: Forward EV/EBITDA (FY27E) | B25: 700 | C25: ='DCF Valuation'!C68 -> 967.4109 | D25: 1170 | E25: 0.5 | F25: =C25*E25 -> 483.70545 | G25: 40x × FY27E EBITDA ₹371Cr; links directly to DCF sheet Part 4 (cell C68)
A27: BLENDED TARGET PRICE — 50% P/E + 50% EV/EBITDA | C27: =SUMPRODUCT(C24:C25,E24:E25)/SUMPRODUCT(E24:E25) -> 933.22468
A28: Current Market Price — CMP (INR) | C28: 883
A29: Upside / (Downside) to Target | C29: =C27/C28-1 -> 0.056879592
A30: INTERPRETATION | B30: DCF intrinsic (₹180-250) represents the FLOOR value. TDPS trades at ~4x intrinsic because the market is pricing in 10-15 years of strong growth, re-rating as an export compounder. Forward multiple valuation (₹933) is the RELEVANT 12-month target — it anchors to market-derived multiples on FY27E earnings. The premium to peer median (P/E 58%, EV/EBITDA 92%) is justified by superior EPS CAGR (25%+), net cash balance sheet, and structural export expansion.
A31: ✓ CROSS-CHECK: Target price in this sheet (C27) = Target price in DCF sheet (C70) — both link to the same underlying FY27E estimates in rows 57-64 of DCF sheet. Change any blue input cell to run scenarios.

Sheet Scenarios
A1: TD POWER SYSTEMS | SCENARIO ANALYSIS
A3: Metric / Assumption | B3: Bear Case | C3: Base Case | D3: Bull Case | E3: Commentary
A4: Revenue CAGR FY25-30E | B4: 12% | C4: 18% | D4: 25% | E4: Bull: Full Plant 3 ramp + export surge
A5: FY30E Revenue (INR Cr) | B5: 2,250 | C5: 2,920 | D5: 3,850 | E5: Bear: Demand softness + FX headwind
A6: EBITDA Margin (FY30E) | B6: 16% | C6: 20% | D6: 22% | E6: Bull: Premium mix, large units, exports
A7: FY30E EBITDA (INR Cr) | B7: 360 | C7: 584 | D7: 847
A8: Terminal Growth Rate | B8: 3.5% | C8: 5.0% | D8: 6.5% | E8: India nominal GDP-linked
A9: WACC | B9: 13% | C9: 12% | D9: 11% | E9: Bull: rating upgrade, lower risk
A10: Intrinsic Value/Share | B10: 620 | C10: ₹180-250 (DCF floor) | D10: ₹960 (Forward P/E primary) | E10: Wide range reflects growth optionality
A11: EV/EBITDA (Exit Mult.) | B11: 20x | C11: 28x | D11: 38x | E11: Comps range 20-50x for quality capex
A12: Target P/E (FY27E) | B12: 40 | C12: 55 | D12: 60 | E12: Bull: rerating on export dominance
A13: FY27E EPS (INR) | B13: 14 | C13: 16.35 | D13: 22 | E13: Estimates
A14: P/E Implied Price | B14: =B12*B13 -> 560 | C14: =C12*C13 -> 899.25 | D14: =D12*D13 -> 1320
A15: Probability Weight | B15: 20% | C15: 55% | D15: 25% | E15: Analyst's scenario probability
A16: Wtd. Target Price | B16: =B14*B15 -> 112 | C16: =C14*C15 -> 494.5875 | D16: =D14*D15 -> 330 | E16: =SUM(B16:D16) -> 936.5875
E17: our target price = 933

Sheet Ratio Dashboard
A1: TD POWER SYSTEMS | KEY FINANCIAL RATIOS & KPIs
A3: Ratio | B3: FY19 | C3: FY20 | D3: FY21 | E3: FY22 | F3: FY23 | G3: FY24 | H3: FY25 | I3: Trend
A4: PROFITABILITY
A5: Revenue (INR Cr) | B5: 459 | C5: 515 | D5: 594 | E5: 797 | F5: 872 | G5: 1001 | H5: 1279 | I5: ↑
A6: EBITDA (INR Cr) | B6: 30 | C6: 38 | D6: 71 | E6: 97 | F6: 134 | G6: 171 | H6: 235 | I6: ↑
A7: EBITDA Margin | B7: 6.5% | C7: 7.4% | D7: 12.0% | E7: 12.2% | F7: 15.4% | G7: 17.1% | H7: 18.4% | I7: ↑↑
A8: PAT (INR Cr) | B8: 3 | C8: 30 | D8: 45 | E8: 70 | F8: 97 | G8: 118 | H8: 175 | I8: ↑
A9: PAT Margin | B9: 0.7% | C9: 5.8% | D9: 7.6% | E9: 8.8% | F9: 11.1% | G9: 11.8% | H9: 13.7% | I9: ↑↑
A10: ROCE (%) | B10: 4.1% | C10: 5.8% | D10: 11.2% | E10: 16.2% | F10: 22.5% | G10: 26.8% | H10: 0.25 | I10: →
A11: ROE (%) | B11: 0.7% | C11: 7.6% | D11: 11.0% | E11: 15.0% | F11: 18.7% | G11: 19.4% | H11: 22.3% | I11: ↑↑
A13: EFFICIENCY
A14: Asset Turnover (x) | B14: ='Historical Financials'!B5/'Historical Financials'!B29 -> 0.65948276 | C14: ='Historical Financials'!C5/'Historical Financials'!C29 -> 0.68302387 | D14: ='Historical Financials'!D5/'Historical Financials'!D29 -> 0.7566879 | E14: ='Historical Financials'!E5/'Historical Financials'!E29 -> 0.92459397 | F14: ='Historical Financials'!F5/'Historical Financials'!F29 -> 0.93763441 | G14: ='Historical Financials'!G5/'Historical Financials'!G29 -> 0.91165756 | H14: ='Historical Financials'!H5/'Historical Financials'!H29 -> 0.96893939 | I14: →
A15: Inventory Days | B15: 62 | C15: 58 | D15: 54 | E15: 48 | F15: 52 | G15: 55 | H15: 50 | I15: ↓
A16: Receivable Days | B16: 110 | C16: 108 | D16: 105 | E16: 98 | F16: 92 | G16: 88 | H16: 80 | I16: ↓
A17: Payable Days | B17: 60 | C17: 65 | D17: 60 | E17: 58 | F17: 55 | G17: 50 | H17: 50 | I17: →
A18: Cash Conversion Cycle | B18: 112 | C18: 101 | D18: 99 | E18: 88 | F18: 89 | G18: 93 | H18: 80 | I18: ↓
A19: Capex/Revenue (%) | B19: =ABS('Historical Financials'!B38)/'Historical Financials'!B5 -> 0.02832244 | C19: =ABS('Historical Financials'!C38)/'Historical Financials'!C5 -> 0.025242718 | D19: =ABS('Historical Financials'!D38)/'Historical Financials'!D5 -> 0.025252525 | E19: =ABS('Historical Financials'!E38)/'Historical Financials'!E5 -> 0.018820577 | F19: =ABS('Historical Financials'!F38)/'Historical Financials'!F5 -> 0.024082569 | G19: =ABS('Historical Financials'!G38)/'Historical Financials'!G5 -> 0.044955045 | H19: =ABS('Historical Financials'!H38)/'Historical Financials'!H5 -> 0.043784206 | I19: →
A21: LEVERAGE & LIQUIDITY
A22: Net Debt (INR Cr) | B22: ='Historical Financials'!B31 -> -23 | C22: ='Historical Financials'!C31 -> -42 | D22: ='Historical Financials'!D31 -> -98 | E22: ='Historical Financials'!E31 -> -119 | F22: ='Historical Financials'!F31 -> -260 | G22: ='Historical Financials'!G31 -> -300 | H22: ='Historical Financials'!H31 -> -268 | I22: →
A23: Net D/EBITDA (x) | B23: =B22/B6 -> -0.76666667 | C23: =C22/C6 -> -1.1052632 | D23: =D22/D6 -> -1.3802817 | E23: =E22/E6 -> -1.2268041 | F23: =F22/F6 -> -1.9402985 | G23: =G22/G6 -> -1.754386 | H23: =H22/H6 -> -1.1404255 | I23: →
A24: Interest Coverage | B24: 5x | C24: 3.8x | D24: 7.9x | E24: 13.9x | F24: 33.5x | G24: 42.8x | H24: 29.4x | I24: ↑
A25: Current Ratio | B25: 2.5 | C25: 2.7 | D25: 2.9 | E25: 3.1 | F25: 3.3 | G25: 3.2 | H25: 3 | I25: →
A26: Quick Ratio | B26: 1.4 | C26: 1.6 | D26: 1.8 | E26: 2 | F26: 2.2 | G26: 2.1 | H26: 2 | I26: →
A28: VALUATION MULTIPLES
A29: P/E (x) | B29: - | C29: - | D29: - | E29: 36 | F29: 22 | G29: 45 | H29: 66.2 | I29: ↑
A30: EV/EBITDA (x) | B30: - | C30: - | D30: - | E30: 18 | F30: 15 | G30: 30 | H30: 49.1 | I30: ↑
A31: P/B (x) | B31: - | C31: - | D31: - | E31: 3.5 | F31: 3.8 | G31: 8.2 | H31: 11.3 | I31: ↑
A32: EV/Revenue (x) | B32: - | C32: - | D32: - | E32: 2.2 | F32: 2.1 | G32: 5.1 | H32: 9.6 | I32: ↑
A33: Dividend Yield (%) | B33: - | C33: - | D33: - | E33: 0.4% | F33: 0.7% | G33: 0.3% | H33: 0.18% | I33: ↓
